biotmed_notification_sdk/__init__.py
biotmed_notification_sdk/api_client.py
biotmed_notification_sdk/api_response.py
biotmed_notification_sdk/configuration.py
biotmed_notification_sdk/exceptions.py
biotmed_notification_sdk/py.typed
biotmed_notification_sdk/rest.py
biotmed_notification_sdk/api/__init__.py
biotmed_notification_sdk/api/configuration_api_api.py
biotmed_notification_sdk/api/email_api_api.py
biotmed_notification_sdk/api/health_check_api_api.py
biotmed_notification_sdk/api/smsapi_api.py
biotmed_notification_sdk/models/__init__.py
biotmed_notification_sdk/models/add_attachment_response.py
biotmed_notification_sdk/models/configuration_request.py
biotmed_notification_sdk/models/configuration_response.py
biotmed_notification_sdk/models/email_request.py
biotmed_notification_sdk/models/email_template.py
biotmed_notification_sdk/models/error_response.py
biotmed_notification_sdk/models/send_sms_request.py
biotmed_notification_sdk/models/send_sms_response.py
biotmed_notification_sdk/models/sms_provider_configuration_response.py
biotmed_notification_sdk/models/version_response.py
biotmed_notification_sdk-2.3.40.dist-info/METADATA
biotmed_notification_sdk-2.3.40.dist-info/WHEEL
biotmed_notification_sdk-2.3.40.dist-info/top_level.txt
biotmed_notification_sdk-2.3.40.dist-info/RECORD
